{
  "rdvs": [
    {
      "id": 1,
      "title": "test",
      "comment": "comment",
      "date": "1646999603557"
    },
    {
      "id": 2,
      "title": "test 2",
      "comment": "comment 2",
      "date": "1645999603557"
    },
    {
      "title": "sqdsqd",
      "comment": "qsdqsdqsd",
      "date": "1647302400000",
      "id": 3
    },
    {
      "title": "Coooo",
      "comment": "ssssss",
      "date": "1647907200000",
      "id": 4
    },
    {
      "title": "sqdsd",
      "comment": "sqdsd",
      "date": "1647388800000",
      "id": 5
    },
    {
      "title": "sqdqsd",
      "comment": "sqddddd",
      "date": "1646697600000",
      "id": 6
    },
    {
      "title": "sdqsd",
      "comment": "sqdsd",
      "date": "1648080000000",
      "id": 7
    }
  ]
}